mla/__init__.py
mla/__init__.pyi
mla/mla.cpython-314-darwin.so
mla/py.typed
mla_archive-0.5.0.dist-info/METADATA
mla_archive-0.5.0.dist-info/WHEEL
mla_archive-0.5.0.dist-info/licenses/LICENSE.md
mla_archive-0.5.0.dist-info/RECORD
