Metadata-Version: 2.4
Name: mla-archive
Version: 0.5.0
Classifier: Programming Language :: Rust
Classifier: Programming Language :: Python :: Implementation :: CPython
Classifier: Programming Language :: Python :: Implementation :: PyPy
License-File: LICENSE.md
Summary: Bindings for MLA Archive manipulation
Keywords: rust,compression,encryption,signature,pqc
Home-Page: https://github.com/ANSSI-FR/MLA
Author-email: ANSSI <opensource@ssi.gouv.fr>
Requires-Python: >=3.11
Project-URL: documentation, https://github.com/ANSSI-FR/MLA
Project-URL: repository, https://github.com/ANSSI-FR/MLA
